movingpeople/__init__.py
movingpeople/src/__init__.py
movingpeople/src/route_generator.py
movingpeople/tests/__init__.py
movingpeople/tests/test_movingpeople.py
movingpeople-0.0.11.dist-info/LICENSE
movingpeople-0.0.11.dist-info/METADATA
movingpeople-0.0.11.dist-info/WHEEL
movingpeople-0.0.11.dist-info/top_level.txt
movingpeople-0.0.11.dist-info/RECORD
