Metadata-Version: 2.1
Name: movingpeople
Version: 0.0.11
Summary: Generate synthetic timesstamped routes on a graph network.
Home-page: https://movingpeople.readthedocs.io/en/latest/index.html
Author: Elliot H
Author-email: elz1582@gmail.com
License: MIT
Classifier: License :: OSI Approved :: MIT License
Classifier: Programming Language :: Python :: 3.10
Classifier: Operating System :: OS Independent
Requires-Python: >=3.10
License-File: LICENSE
Requires-Dist: osmnx (>=1.5.0)
Requires-Dist: shapely (>=2.0.1)
Requires-Dist: geopandas (>=0.13.2)
Requires-Dist: numpy (>=1.25.0)
Requires-Dist: keplergl (>=0.3.2)
Requires-Dist: pandas (>=2.0.3)
Provides-Extra: dev
Requires-Dist: pytest (>=7.0) ; extra == 'dev'
Requires-Dist: twine (>=4.0.2) ; extra == 'dev'
